Assignment7/verilog/encoder_ip.v
module encoder_ip (
    input clk,
    input rst,
    input enc_a,
    input enc_b,
    output reg[31:0] counter = 0,
    output reg direction = 0
);

reg enc_a_sync1, enc_a_sync2;
reg enc_b_sync1, enc_b_sync2;
reg [1:0] prev_state = 0;
reg [1:0] state = 0;

always @(posedge clk or posedge rst) begin
    if (rst) begin
        enc_a_sync1 <= 0;
        enc_a_sync2 <= 0;
        enc_b_sync1 <= 0;
        enc_b_sync2 <= 0;
        counter <= 32'b0;
        prev_state <= 2'b00;
        state <= 2'b00;
    end else begin
        
        enc_a_sync1 <= enc_a;
        enc_b_sync1 <= enc_b;
        
        enc_a_sync2 <= enc_a_sync1;
        enc_b_sync2 <= enc_b_sync1;
        
        
        state <= {enc_a_sync2, enc_b_sync2};
        prev_state <= state;
        
        case ({prev_state, state}) 
            4'b0010,4'b1011,4'b1101,4'b0100: begin 
                direction <= 1'b1; 
                counter <= counter + 32'b1;
            end
            4'b0001,4'b0111,4'b1110,4'b1000: begin 
                direction <= 1'b0;
                counter <= counter - 32'b1;
            end
        endcase
    end
end

endmodule

Assignment7/verilog/tb.v
`include "encoder_ip.v"

module tb();

reg clk;
reg rst;

reg enc_a;
reg enc_b;

wire [31:0] counter;
wire direction;
integer i;

encoder_ip dut (.clk(clk), .rst(rst), .enc_a(enc_a),.enc_b(enc_b),
                .counter(counter), .direction(direction));

always #5 clk = ~clk;

always@(counter) begin 
        $display("Counter %d : Direction %s",counter,direction ? "CW":"CCW");
    end

initial begin 

    $dumpfile("signals.vcd");
    $dumpvars(0,tb);

    clk = 0;
    enc_a = 0;
    enc_b = 0;

    for (i = 0; i<10; i = i+1) begin 
    #10 enc_a = 0; enc_b = 0;
    #10 enc_a = 1; enc_b = 0;
    #10 enc_a = 1; enc_b = 1;
    #10 enc_a = 0; enc_b = 1;

    end

    for (i = 10; i>0; i= i-1) begin 
    #10 enc_a = 0; enc_b = 0;
    #10 enc_a = 0; enc_b = 1;
    #10 enc_a = 1; enc_b = 1;
    #10 enc_a = 1; enc_b = 0;

    end

    #50 $finish;

end

endmodule

Assignment7/verilog/signals.vcd
$date
	Fri May  8 22:50:03 2026
$end
$version
	Icarus Verilog
$end
$timescale
	1s
$end
$scope module tb $end
$var wire 1 ! direction $end
$var wire 32 " counter [31:0] $end
$var reg 1 # clk $end
$var reg 1 $ enc_a $end
$var reg 1 % enc_b $end
$var reg 1 & rst $end
$var integer 32 ' i [31:0] $end
$scope module dut $end
$var wire 1 # clk $end
$var wire 1 $ enc_a $end
$var wire 1 % enc_b $end
$var wire 1 & rst $end
$var reg 32 ( counter [31:0] $end
$var reg 1 ! direction $end
$var reg 1 ) enc_a_sync1 $end
$var reg 1 * enc_a_sync2 $end
$var reg 1 + enc_b_sync1 $end
$var reg 1 , enc_b_sync2 $end
$var reg 2 - prev_state [1:0] $end
$var reg 2 . state [1:0] $end
$upscope $end
$upscope $end
$enddefinitions $end
$comment Show the parameter values. $end
$dumpall
$end
#0
$dumpvars
b0 .
b0 -
x,
x+
x*
x)
b0 (
b0 '
x&
0%
0$
0#
b0 "
0!
$end
#5
bx .
0+
0)
1#
#10
0#
#15
bx -
0,
0*
1#
#20
0#
1$
#25
b0 .
1)
1#
#30
0#
1%
#35
b0 -
1*
1+
1#
#40
0#
b1 '
0$
#45
b10 .
1,
0)
1#
#50
0#
0%
#55
b1 "
b1 (
1!
b10 -
b11 .
0*
0+
1#
#60
0#
1$
#65
b10 "
b10 (
b11 -
b1 .
0,
1)
1#
#70
0#
1%
#75
b11 "
b11 (
b1 -
b0 .
1*
1+
1#
#80
0#
b10 '
0$
#85
b100 "
b100 (
b0 -
b10 .
1,
0)
1#
#90
0#
0%
#95
b101 "
b101 (
b10 -
b11 .
0*
0+
1#
#100
0#
1$
#105
b110 "
b110 (
b11 -
b1 .
0,
1)
1#
#110
0#
1%
#115
b111 "
b111 (
b1 -
b0 .
1*
1+
1#
#120
0#
b11 '
0$
#125
b1000 "
b1000 (
b0 -
b10 .
1,
0)
1#
#130
0#
0%
#135
b1001 "
b1001 (
b10 -
b11 .
0*
0+
1#
#140
0#
1$
#145
b1010 "
b1010 (
b11 -
b1 .
0,
1)
1#
#150
0#
1%
#155
b1011 "
b1011 (
b1 -
b0 .
1*
1+
1#
#160
0#
b100 '
0$
#165
b1100 "
b1100 (
b0 -
b10 .
1,
0)
1#
#170
0#
0%
#175
b1101 "
b1101 (
b10 -
b11 .
0*
0+
1#
#180
0#
1$
#185
b1110 "
b1110 (
b11 -
b1 .
0,
1)
1#
#190
0#
1%
#195
b1111 "
b1111 (
b1 -
b0 .
1*
1+
1#
#200
0#
b101 '
0$
#205
b10000 "
b10000 (
b0 -
b10 .
1,
0)
1#
#210
0#
0%
#215
b10001 "
b10001 (
b10 -
b11 .
0*
0+
1#
#220
0#
1$
#225
b10010 "
b10010 (
b11 -
b1 .
0,
1)
1#
#230
0#
1%
#235
b10011 "
b10011 (
b1 -
b0 .
1*
1+
1#
#240
0#
b110 '
0$
#245
b10100 "
b10100 (
b0 -
b10 .
1,
0)
1#
#250
0#
0%
#255
b10101 "
b10101 (
b10 -
b11 .
0*
0+
1#
#260
0#
1$
#265
b10110 "
b10110 (
b11 -
b1 .
0,
1)
1#
#270
0#
1%
#275
b10111 "
b10111 (
b1 -
b0 .
1*
1+
1#
#280
0#
b111 '
0$
#285
b11000 "
b11000 (
b0 -
b10 .
1,
0)
1#
#290
0#
0%
#295
b11001 "
b11001 (
b10 -
b11 .
0*
0+
1#
#300
0#
1$
#305
b11010 "
b11010 (
b11 -
b1 .
0,
1)
1#
#310
0#
1%
#315
b11011 "
b11011 (
b1 -
b0 .
1*
1+
1#
#320
0#
b1000 '
0$
#325
b11100 "
b11100 (
b0 -
b10 .
1,
0)
1#
#330
0#
0%
#335
b11101 "
b11101 (
b10 -
b11 .
0*
0+
1#
#340
0#
1$
#345
b11110 "
b11110 (
b11 -
b1 .
0,
1)
1#
#350
0#
1%
#355
b11111 "
b11111 (
b1 -
b0 .
1*
1+
1#
#360
0#
b1001 '
0$
#365
b100000 "
b100000 (
b0 -
b10 .
1,
0)
1#
#370
0#
0%
#375
b100001 "
b100001 (
b10 -
b11 .
0*
0+
1#
#380
0#
1$
#385
b100010 "
b100010 (
b11 -
b1 .
0,
1)
1#
#390
0#
1%
#395
b100011 "
b100011 (
b1 -
b0 .
1*
1+
1#
#400
0#
b1010 '
0$
#405
b100100 "
b100100 (
b0 -
b10 .
1,
0)
1#
#410
0#
0%
#415
b100101 "
b100101 (
b10 -
b11 .
0*
0+
1#
#420
0#
1%
#425
b100110 "
b100110 (
b11 -
b1 .
0,
1+
1#
#430
0#
1$
#435
b100111 "
b100111 (
b1 -
b0 .
1,
1)
1#
#440
0#
b1001 '
0%
#445
b101000 "
b101000 (
b0 -
b1 .
1*
0+
1#
#450
0#
0$
#455
b100111 "
b100111 (
0!
b1 -
b11 .
0,
0)
1#
#460
0#
1%
#465
b100110 "
b100110 (
b11 -
b10 .
0*
1+
1#
#470
0#
1$
#475
b100101 "
b100101 (
b10 -
b0 .
1,
1)
1#
#480
0#
b1000 '
0%
#485
b100100 "
b100100 (
b0 -
b1 .
1*
0+
1#
#490
0#
0$
#495
b100011 "
b100011 (
b1 -
b11 .
0,
0)
1#
#500
0#
1%
#505
b100010 "
b100010 (
b11 -
b10 .
0*
1+
1#
#510
0#
1$
#515
b100001 "
b100001 (
b10 -
b0 .
1,
1)
1#
#520
0#
b111 '
0%
#525
b100000 "
b100000 (
b0 -
b1 .
1*
0+
1#
#530
0#
0$
#535
b11111 "
b11111 (
b1 -
b11 .
0,
0)
1#
#540
0#
1%
#545
b11110 "
b11110 (
b11 -
b10 .
0*
1+
1#
#550
0#
1$
#555
b11101 "
b11101 (
b10 -
b0 .
1,
1)
1#
#560
0#
b110 '
0%
#565
b11100 "
b11100 (
b0 -
b1 .
1*
0+
1#
#570
0#
0$
#575
b11011 "
b11011 (
b1 -
b11 .
0,
0)
1#
#580
0#
1%
#585
b11010 "
b11010 (
b11 -
b10 .
0*
1+
1#
#590
0#
1$
#595
b11001 "
b11001 (
b10 -
b0 .
1,
1)
1#
#600
0#
b101 '
0%
#605
b11000 "
b11000 (
b0 -
b1 .
1*
0+
1#
#610
0#
0$
#615
b10111 "
b10111 (
b1 -
b11 .
0,
0)
1#
#620
0#
1%
#625
b10110 "
b10110 (
b11 -
b10 .
0*
1+
1#
#630
0#
1$
#635
b10101 "
b10101 (
b10 -
b0 .
1,
1)
1#
#640
0#
b100 '
0%
#645
b10100 "
b10100 (
b0 -
b1 .
1*
0+
1#
#650
0#
0$
#655
b10011 "
b10011 (
b1 -
b11 .
0,
0)
1#
#660
0#
1%
#665
b10010 "
b10010 (
b11 -
b10 .
0*
1+
1#
#670
0#
1$
#675
b10001 "
b10001 (
b10 -
b0 .
1,
1)
1#
#680
0#
b11 '
0%
#685
b10000 "
b10000 (
b0 -
b1 .
1*
0+
1#
#690
0#
0$
#695
b1111 "
b1111 (
b1 -
b11 .
0,
0)
1#
#700
0#
1%
#705
b1110 "
b1110 (
b11 -
b10 .
0*
1+
1#
#710
0#
1$
#715
b1101 "
b1101 (
b10 -
b0 .
1,
1)
1#
#720
0#
b10 '
0%
#725
b1100 "
b1100 (
b0 -
b1 .
1*
0+
1#
#730
0#
0$
#735
b1011 "
b1011 (
b1 -
b11 .
0,
0)
1#
#740
0#
1%
#745
b1010 "
b1010 (
b11 -
b10 .
0*
1+
1#
#750
0#
1$
#755
b1001 "
b1001 (
b10 -
b0 .
1,
1)
1#
#760
0#
b1 '
0%
#765
b1000 "
b1000 (
b0 -
b1 .
1*
0+
1#
#770
0#
0$
#775
b111 "
b111 (
b1 -
b11 .
0,
0)
1#
#780
0#
1%
#785
b110 "
b110 (
b11 -
b10 .
0*
1+
1#
#790
0#
1$
#795
b101 "
b101 (
b10 -
b0 .
1,
1)
1#
#800
0#
b0 '
0%
#805
b100 "
b100 (
b0 -
b1 .
1*
0+
1#
#810
0#
#815
b11 "
b11 (
b1 -
b11 .
0,
1#
#820
0#
#825
b10 "
b10 (
b11 -
b10 .
1#
#830
0#
#835
b1 "
b1 (
b10 -
1#
