Assignment4/quadrature_enc.v
module quadrature_enc (
    input clk,
    input enc_a,
    input enc_b,
    output reg[31:0] counter = 0,
    output reg direction = 0);

reg enc_a_prev = 0;

always @(posedge clk) begin

    if (enc_a == 1 && enc_a_prev == 0) begin

        if (enc_b == 0) begin

            direction <= 1;
            counter <= counter + 1;

        end

        else begin

            direction <= 0;
            counter <= counter - 1;

        end


    end

    enc_a_prev = enc_a;

end


endmodule

Assignment4/quadrature_enc_tb.v
`include "quadrature_enc.v"

module quadrature_enc_tb();

reg clk;
reg enc_a;
reg enc_b;
wire direction;
wire [31:0] counter;

integer i;

quadrature_enc dut (.clk(clk),.enc_a(enc_a),.enc_b(enc_b),
                        .direction(direction),
                        .counter(counter));

always #5 clk = ~clk;

initial begin

    $dumpfile("signals.vcd");
    $dumpvars(0, quadrature_enc_tb);

    clk = 0;
    enc_a = 0;
    enc_b = 0;



    for (i = 0; i < 10; i = i + 1) begin

        #10 enc_a = 1;
        #10 enc_b = 1;
        #10 enc_a = 0;
        #10 enc_b = 0;

    end

    for (i = 10; i >0; i = i - 1) begin

        #10 enc_b = 1;
        #10 enc_a = 1;
        #10 enc_b = 0;
        #10 enc_a = 0;


    end

    #50 $finish;

    
end
endmodule

Assignment4/signals.vcd
$date
	Thu Apr 30 09:23:44 2026
$end
$version
	Icarus Verilog
$end
$timescale
	1s
$end
$scope module quadrature_enc_tb $end
$var wire 1 ! direction $end
$var wire 32 " counter [31:0] $end
$var reg 1 # clk $end
$var reg 1 $ enc_a $end
$var reg 1 % enc_b $end
$var integer 32 & i [31:0] $end
$scope module dut $end
$var wire 1 # clk $end
$var wire 1 $ enc_a $end
$var wire 1 % enc_b $end
$var reg 32 ' counter [31:0] $end
$var reg 1 ! direction $end
$var reg 1 ( enc_a_prev $end
$upscope $end
$upscope $end
$enddefinitions $end
$comment Show the parameter values. $end
$dumpall
$end
#0
$dumpvars
0(
b0 '
b0 &
0%
0$
0#
b0 "
0!
$end
#5
1#
#10
0#
1$
#15
b1 "
b1 '
1!
1(
1#
#20
0#
1%
#25
1#
#30
0#
0$
#35
0(
1#
#40
0#
b1 &
0%
#45
1#
#50
0#
1$
#55
b10 "
b10 '
1(
1#
#60
0#
1%
#65
1#
#70
0#
0$
#75
0(
1#
#80
0#
b10 &
0%
#85
1#
#90
0#
1$
#95
b11 "
b11 '
1(
1#
#100
0#
1%
#105
1#
#110
0#
0$
#115
0(
1#
#120
0#
b11 &
0%
#125
1#
#130
0#
1$
#135
b100 "
b100 '
1(
1#
#140
0#
1%
#145
1#
#150
0#
0$
#155
0(
1#
#160
0#
b100 &
0%
#165
1#
#170
0#
1$
#175
b101 "
b101 '
1(
1#
#180
0#
1%
#185
1#
#190
0#
0$
#195
0(
1#
#200
0#
b101 &
0%
#205
1#
#210
0#
1$
#215
b110 "
b110 '
1(
1#
#220
0#
1%
#225
1#
#230
0#
0$
#235
0(
1#
#240
0#
b110 &
0%
#245
1#
#250
0#
1$
#255
b111 "
b111 '
1(
1#
#260
0#
1%
#265
1#
#270
0#
0$
#275
0(
1#
#280
0#
b111 &
0%
#285
1#
#290
0#
1$
#295
b1000 "
b1000 '
1(
1#
#300
0#
1%
#305
1#
#310
0#
0$
#315
0(
1#
#320
0#
b1000 &
0%
#325
1#
#330
0#
1$
#335
b1001 "
b1001 '
1(
1#
#340
0#
1%
#345
1#
#350
0#
0$
#355
0(
1#
#360
0#
b1001 &
0%
#365
1#
#370
0#
1$
#375
b1010 "
b1010 '
1(
1#
#380
0#
1%
#385
1#
#390
0#
0$
#395
0(
1#
#400
0#
b1010 &
0%
#405
1#
#410
0#
1%
#415
1#
#420
0#
1$
#425
b1001 "
b1001 '
0!
1(
1#
#430
0#
0%
#435
1#
#440
0#
b1001 &
0$
#445
0(
1#
#450
0#
1%
#455
1#
#460
0#
1$
#465
b1000 "
b1000 '
1(
1#
#470
0#
0%
#475
1#
#480
0#
b1000 &
0$
#485
0(
1#
#490
0#
1%
#495
1#
#500
0#
1$
#505
b111 "
b111 '
1(
1#
#510
0#
0%
#515
1#
#520
0#
b111 &
0$
#525
0(
1#
#530
0#
1%
#535
1#
#540
0#
1$
#545
b110 "
b110 '
1(
1#
#550
0#
0%
#555
1#
#560
0#
b110 &
0$
#565
0(
1#
#570
0#
1%
#575
1#
#580
0#
1$
#585
b101 "
b101 '
1(
1#
#590
0#
0%
#595
1#
#600
0#
b101 &
0$
#605
0(
1#
#610
0#
1%
#615
1#
#620
0#
1$
#625
b100 "
b100 '
1(
1#
#630
0#
0%
#635
1#
#640
0#
b100 &
0$
#645
0(
1#
#650
0#
1%
#655
1#
#660
0#
1$
#665
b11 "
b11 '
1(
1#
#670
0#
0%
#675
1#
#680
0#
b11 &
0$
#685
0(
1#
#690
0#
1%
#695
1#
#700
0#
1$
#705
b10 "
b10 '
1(
1#
#710
0#
0%
#715
1#
#720
0#
b10 &
0$
#725
0(
1#
#730
0#
1%
#735
1#
#740
0#
1$
#745
b1 "
b1 '
1(
1#
#750
0#
0%
#755
1#
#760
0#
b1 &
0$
#765
0(
1#
#770
0#
1%
#775
1#
#780
0#
1$
#785
b0 "
b0 '
1(
1#
#790
0#
0%
#795
1#
#800
0#
b0 &
0$
#805
0(
1#
