Assignment9/verilog/pwm_mod.v
module pwm_mod #(parameter PWM_FREQ = 20_000,
                 parameter CLK_FREQ = 50_000_000)(
    input  wire       clk,
    input  wire       rst,
    input  wire       enable,
    input  wire [6:0] duty_cycle,
    input  wire       direction,

    output reg        INA,
    output reg        INB,
    output reg        pwm_out
);

localparam integer PERIOD_SCALED = (CLK_FREQ / PWM_FREQ) / 100; 

reg [12:0] counter;

always @(posedge clk or posedge rst) begin
    if (rst) begin
        counter <= 0;
        INA     <= 1'b0;
        INB     <= 1'b0;
        pwm_out <= 1'b0;
    end else begin
        if (!enable) begin
            counter <= 0;
            INA     <= 1'b0;
            INB     <= 1'b0;
            pwm_out <= 1'b0;
        end else begin
           
            INA <= (direction == 1'b0) ? 1'b1 : 1'b0;
            INB <= (direction == 1'b0) ? 1'b0 : 1'b1;

           
            if (counter >= (PERIOD_SCALED * 100) - 1)
                counter <= 0;
            else
                counter <= counter + 1;

            
            pwm_out <= (counter < duty_cycle * PERIOD_SCALED) ? 1'b1 : 1'b0;
        end
    end
end

endmodule

Assignment9/verilog/tb.v
`timescale 1ns / 1ps
// -----------------------------------------------------------------------------
// pwm_mod_tb.v  –  Testbench for pwm_mod
//
// Tests:
//   1. Reset behaviour        – all outputs low
//   2. Disabled               – all outputs low, counter held at 0
//   3. Forward  25% duty      – INA=1, INB=0, pwm_out high 25% of period
//   4. Forward  50% duty      – INA=1, INB=0, pwm_out high 50% of period
//   5. Forward 100% duty      – INA=1, INB=0, pwm_out always high
//   6. Reverse  50% duty      – INA=0, INB=1, pwm_out high 50% of period
//   7. 0% duty                – pwm_out always low, INA/INB still driven
//
// Simulate with:
//   iverilog -o pwm_mod_tb.vvp pwm_mod_tb.v pwm_mod.v
//   vvp pwm_mod_tb.vvp
//   gtkwave signals.vcd
// -----------------------------------------------------------------------------

`include "pwm_mod.v"

module pwm_mod_tb;

    // -------------------------------------------------------------------------
    // Use small parameters so simulation runs in microseconds, not seconds.
    // PERIOD_SCALED = CLK_FREQ / PWM_FREQ / 100 = 1000 / 10 / 100 = 1
    // One full PWM period = 100 counter ticks = 100 * 2 ns = 200 ns
    // -------------------------------------------------------------------------
    localparam CLK_FREQ = 1_000;   // 1 kHz – tiny, fast simulation
    localparam PWM_FREQ = 10;      // 10 Hz  – PERIOD = 100 ticks

    // DUT signals
    reg        clk       = 0;
    reg        rst       = 0;
    reg        enable    = 0;
    reg  [6:0] duty_cycle = 0;
    reg        direction = 0;
    wire       INA;
    wire       INB;
    wire       pwm_out;

    // Instantiate DUT
    pwm_mod #(
        .PWM_FREQ(PWM_FREQ),
        .CLK_FREQ(CLK_FREQ)
    ) dut (
        .clk       (clk),
        .rst       (rst),
        .enable    (enable),
        .duty_cycle(duty_cycle),
        .direction (direction),
        .INA       (INA),
        .INB       (INB),
        .pwm_out   (pwm_out)
    );

    // 2 ns clock period
    always #1 clk = ~clk;

    // -------------------------------------------------------------------------
    // Utility task: run for N full PWM periods and count pwm_out high cycles
    // -------------------------------------------------------------------------
    integer high_count;
    integer total_count;

    task run_and_measure;
        input integer periods;
        input integer period_ticks;
        begin
            high_count  = 0;
            total_count = periods * period_ticks;
            repeat (total_count) begin
                @(posedge clk);
                if (pwm_out) high_count = high_count + 1;
            end
        end
    endtask

    // -------------------------------------------------------------------------
    // Check helper: print PASS / FAIL
    // -------------------------------------------------------------------------
    task check;
        input [127:0] test_name;
        input         condition;
        begin
            if (condition)
                $display("PASS  %0s", test_name);
            else
                $display("FAIL  %0s", test_name);
        end
    endtask

    // -------------------------------------------------------------------------
    // Main stimulus
    // -------------------------------------------------------------------------
    localparam PERIOD_TICKS = CLK_FREQ / PWM_FREQ; // 100 ticks per period

    initial begin
        $dumpfile("signals.vcd");
        $dumpvars(0, pwm_mod_tb);

        // ------------------------------------------------------------------
        // Test 1: Reset
        // ------------------------------------------------------------------
        rst = 1;
        @(posedge clk); @(posedge clk);
        check("Reset: INA=0",     INA     == 1'b0);
        check("Reset: INB=0",     INB     == 1'b0);
        check("Reset: pwm_out=0", pwm_out == 1'b0);
        rst = 0;

        // ------------------------------------------------------------------
        // Test 2: Disabled (enable=0)
        // ------------------------------------------------------------------
        enable    = 0;
        duty_cycle = 50;
        direction = 0;
        repeat (PERIOD_TICKS * 2) @(posedge clk);
        check("Disabled: INA=0",     INA     == 1'b0);
        check("Disabled: INB=0",     INB     == 1'b0);
        check("Disabled: pwm_out=0", pwm_out == 1'b0);

        // ------------------------------------------------------------------
        // Test 3: Forward, 25% duty
        // ------------------------------------------------------------------
        enable    = 1;
        direction = 0;
        duty_cycle = 25;
        // Wait one period for counter to settle, then measure 4 periods
        repeat (PERIOD_TICKS) @(posedge clk);
        run_and_measure(4, PERIOD_TICKS);
        check("Fwd 25%: INA=1",   INA == 1'b1);
        check("Fwd 25%: INB=0",   INB == 1'b0);
        // Allow ±2 ticks tolerance due to off-by-one at wrap boundary
        check("Fwd 25%: duty",    high_count >= (total_count*25/100 - 2) &&
                                  high_count <= (total_count*25/100 + 2));
        $display("      measured %0d / %0d high ticks (~%0d%%)",
                 high_count, total_count, high_count*100/total_count);

        // ------------------------------------------------------------------
        // Test 4: Forward, 50% duty
        // ------------------------------------------------------------------
        duty_cycle = 50;
        repeat (PERIOD_TICKS) @(posedge clk);
        run_and_measure(4, PERIOD_TICKS);
        check("Fwd 50%: duty",    high_count >= (total_count*50/100 - 2) &&
                                  high_count <= (total_count*50/100 + 2));
        $display("      measured %0d / %0d high ticks (~%0d%%)",
                 high_count, total_count, high_count*100/total_count);

        // ------------------------------------------------------------------
        // Test 5: Forward, 100% duty
        // ------------------------------------------------------------------
        duty_cycle = 100;
        repeat (PERIOD_TICKS) @(posedge clk);
        run_and_measure(4, PERIOD_TICKS);
        check("Fwd 100%: pwm always high", high_count == total_count);
        $display("      measured %0d / %0d high ticks (~%0d%%)",
                 high_count, total_count, high_count*100/total_count);

        // ------------------------------------------------------------------
        // Test 6: Reverse, 50% duty
        // ------------------------------------------------------------------
        direction  = 1;
        duty_cycle = 50;
        repeat (PERIOD_TICKS) @(posedge clk);
        run_and_measure(4, PERIOD_TICKS);
        check("Rev 50%: INA=0",   INA == 1'b0);
        check("Rev 50%: INB=1",   INB == 1'b1);
        check("Rev 50%: duty",    high_count >= (total_count*50/100 - 2) &&
                                  high_count <= (total_count*50/100 + 2));
        $display("      measured %0d / %0d high ticks (~%0d%%)",
                 high_count, total_count, high_count*100/total_count);

        // ------------------------------------------------------------------
        // Test 7: 0% duty – pwm_out always low
        // ------------------------------------------------------------------
        direction  = 0;
        duty_cycle = 0;
        repeat (PERIOD_TICKS) @(posedge clk);
        run_and_measure(4, PERIOD_TICKS);
        check("Fwd 0%: INA=1",          INA == 1'b1);
        check("Fwd 0%: pwm always low",  high_count == 0);
        $display("      measured %0d / %0d high ticks", high_count, total_count);

        $display("\nSimulation complete.");
        $finish;
    end

endmodule

Assignment9/verilog/signals.vcd
$date
	Sat May 16 12:14:24 2026
$end
$version
	Icarus Verilog
$end
$timescale
	1ps
$end
$scope module pwm_mod_tb $end
$var wire 1 ! pwm_out $end
$var wire 1 " INB $end
$var wire 1 # INA $end
$var parameter 32 $ CLK_FREQ $end
$var parameter 32 % PERIOD_TICKS $end
$var parameter 32 & PWM_FREQ $end
$var reg 1 ' clk $end
$var reg 1 ( direction $end
$var reg 7 ) duty_cycle [6:0] $end
$var reg 1 * enable $end
$var reg 1 + rst $end
$var integer 32 , high_count [31:0] $end
$var integer 32 - total_count [31:0] $end
$scope module dut $end
$var wire 1 ' clk $end
$var wire 1 ( direction $end
$var wire 7 . duty_cycle [6:0] $end
$var wire 1 * enable $end
$var wire 1 + rst $end
$var parameter 32 / CLK_FREQ $end
$var parameter 32 0 PERIOD_SCALED $end
$var parameter 32 1 PWM_FREQ $end
$var reg 1 # INA $end
$var reg 1 " INB $end
$var reg 13 2 counter [12:0] $end
$var reg 1 ! pwm_out $end
$upscope $end
$scope task check $end
$var reg 1 3 condition $end
$var reg 128 4 test_name [127:0] $end
$upscope $end
$scope task run_and_measure $end
$var integer 32 5 period_ticks [31:0] $end
$var integer 32 6 periods [31:0] $end
$upscope $end
$upscope $end
$enddefinitions $end
$comment Show the parameter values. $end
$dumpall
b1010 1
b1 0
b1111101000 /
b1010 &
b1100100 %
b1111101000 $
$end
#0
$dumpvars
bx 6
bx 5
bx 4
x3
b0 2
b0 .
bx -
bx ,
1+
0*
b0 )
0(
0'
0#
0"
0!
$end
#1000
1'
#2000
0'
#3000
b110010 )
b110010 .
0+
13
b1010010011001010111001101100101011101000011101000100000011100000111011101101101010111110110111101110101011101000011110100110000 4
1'
#4000
0'
#5000
1'
#6000
0'
#7000
1'
#8000
0'
#9000
1'
#10000
0'
#11000
1'
#12000
0'
#13000
1'
#14000
0'
#15000
1'
#16000
0'
#17000
1'
#18000
0'
#19000
1'
#20000
0'
#21000
1'
#22000
0'
#23000
1'
#24000
0'
#25000
1'
#26000
0'
#27000
1'
#28000
0'
#29000
1'
#30000
0'
#31000
1'
#32000
0'
#33000
1'
#34000
0'
#35000
1'
#36000
0'
#37000
1'
#38000
0'
#39000
1'
#40000
0'
#41000
1'
#42000
0'
#43000
1'
#44000
0'
#45000
1'
#46000
0'
#47000
1'
#48000
0'
#49000
1'
#50000
0'
#51000
1'
#52000
0'
#53000
1'
#54000
0'
#55000
1'
#56000
0'
#57000
1'
#58000
0'
#59000
1'
#60000
0'
#61000
1'
#62000
0'
#63000
1'
#64000
0'
#65000
1'
#66000
0'
#67000
1'
#68000
0'
#69000
1'
#70000
0'
#71000
1'
#72000
0'
#73000
1'
#74000
0'
#75000
1'
#76000
0'
#77000
1'
#78000
0'
#79000
1'
#80000
0'
#81000
1'
#82000
0'
#83000
1'
#84000
0'
#85000
1'
#86000
0'
#87000
1'
#88000
0'
#89000
1'
#90000
0'
#91000
1'
#92000
0'
#93000
1'
#94000
0'
#95000
1'
#96000
0'
#97000
1'
#98000
0'
#99000
1'
#100000
0'
#101000
1'
#102000
0'
#103000
1'
#104000
0'
#105000
1'
#106000
0'
#107000
1'
#108000
0'
#109000
1'
#110000
0'
#111000
1'
#112000
0'
#113000
1'
#114000
0'
#115000
1'
#116000
0'
#117000
1'
#118000
0'
#119000
1'
#120000
0'
#121000
1'
#122000
0'
#123000
1'
#124000
0'
#125000
1'
#126000
0'
#127000
1'
#128000
0'
#129000
1'
#130000
0'
#131000
1'
#132000
0'
#133000
1'
#134000
0'
#135000
1'
#136000
0'
#137000
1'
#138000
0'
#139000
1'
#140000
0'
#141000
1'
#142000
0'
#143000
1'
#144000
0'
#145000
1'
#146000
0'
#147000
1'
#148000
0'
#149000
1'
#150000
0'
#151000
1'
#152000
0'
#153000
1'
#154000
0'
#155000
1'
#156000
0'
#157000
1'
#158000
0'
#159000
1'
#160000
0'
#161000
1'
#162000
0'
#163000
1'
#164000
0'
#165000
1'
#166000
0'
#167000
1'
#168000
0'
#169000
1'
#170000
0'
#171000
1'
#172000
0'
#173000
1'
#174000
0'
#175000
1'
#176000
0'
#177000
1'
#178000
0'
#179000
1'
#180000
0'
#181000
1'
#182000
0'
#183000
1'
#184000
0'
#185000
1'
#186000
0'
#187000
1'
#188000
0'
#189000
1'
#190000
0'
#191000
1'
#192000
0'
#193000
1'
#194000
0'
#195000
1'
#196000
0'
#197000
1'
#198000
0'
#199000
1'
#200000
0'
#201000
1'
#202000
0'
#203000
1'
#204000
0'
#205000
1'
#206000
0'
#207000
1'
#208000
0'
#209000
1'
#210000
0'
#211000
1'
#212000
0'
#213000
1'
#214000
0'
#215000
1'
#216000
0'
#217000
1'
#218000
0'
#219000
1'
#220000
0'
#221000
1'
#222000
0'
#223000
1'
#224000
0'
#225000
1'
#226000
0'
#227000
1'
#228000
0'
#229000
1'
#230000
0'
#231000
1'
#232000
0'
#233000
1'
#234000
0'
#235000
1'
#236000
0'
#237000
1'
#238000
0'
#239000
1'
#240000
0'
#241000
1'
#242000
0'
#243000
1'
#244000
0'
#245000
1'
#246000
0'
#247000
1'
#248000
0'
#249000
1'
#250000
0'
#251000
1'
#252000
0'
#253000
1'
#254000
0'
#255000
1'
#256000
0'
#257000
1'
#258000
0'
#259000
1'
#260000
0'
#261000
1'
#262000
0'
#263000
1'
#264000
0'
#265000
1'
#266000
0'
#267000
1'
#268000
0'
#269000
1'
#270000
0'
#271000
1'
#272000
0'
#273000
1'
#274000
0'
#275000
1'
#276000
0'
#277000
1'
#278000
0'
#279000
1'
#280000
0'
#281000
1'
#282000
0'
#283000
1'
#284000
0'
#285000
1'
#286000
0'
#287000
1'
#288000
0'
#289000
1'
#290000
0'
#291000
1'
#292000
0'
#293000
1'
#294000
0'
#295000
1'
#296000
0'
#297000
1'
#298000
0'
#299000
1'
#300000
0'
#301000
1'
#302000
0'
#303000
1'
#304000
0'
#305000
1'
#306000
0'
#307000
1'
#308000
0'
#309000
1'
#310000
0'
#311000
1'
#312000
0'
#313000
1'
#314000
0'
#315000
1'
#316000
0'
#317000
1'
#318000
0'
#319000
1'
#320000
0'
#321000
1'
#322000
0'
#323000
1'
#324000
0'
#325000
1'
#326000
0'
#327000
1'
#328000
0'
#329000
1'
#330000
0'
#331000
1'
#332000
0'
#333000
1'
#334000
0'
#335000
1'
#336000
0'
#337000
1'
#338000
0'
#339000
1'
#340000
0'
#341000
1'
#342000
0'
#343000
1'
#344000
0'
#345000
1'
#346000
0'
#347000
1'
#348000
0'
#349000
1'
#350000
0'
#351000
1'
#352000
0'
#353000
1'
#354000
0'
#355000
1'
#356000
0'
#357000
1'
#358000
0'
#359000
1'
#360000
0'
#361000
1'
#362000
0'
#363000
1'
#364000
0'
#365000
1'
#366000
0'
#367000
1'
#368000
0'
#369000
1'
#370000
0'
#371000
1'
#372000
0'
#373000
1'
#374000
0'
#375000
1'
#376000
0'
#377000
1'
#378000
0'
#379000
1'
#380000
0'
#381000
1'
#382000
0'
#383000
1'
#384000
0'
#385000
1'
#386000
0'
#387000
1'
#388000
0'
#389000
1'
#390000
0'
#391000
1'
#392000
0'
#393000
1'
#394000
0'
#395000
1'
#396000
0'
#397000
1'
#398000
0'
#399000
1'
#400000
0'
#401000
1'
#402000
0'
#403000
1!
b1 2
1#
b11001 )
b11001 .
1*
b1100001011000100110110001100101011001000011101000100000011100000111011101101101010111110110111101110101011101000011110100110000 4
1'
#404000
0'
#405000
b10 2
1'
#406000
0'
#407000
b11 2
1'
#408000
0'
#409000
b100 2
1'
#410000
0'
#411000
b101 2
1'
#412000
0'
#413000
b110 2
1'
#414000
0'
#415000
b111 2
1'
#416000
0'
#417000
b1000 2
1'
#418000
0'
#419000
b1001 2
1'
#420000
0'
#421000
b1010 2
1'
#422000
0'
#423000
b1011 2
1'
#424000
0'
#425000
b1100 2
1'
#426000
0'
#427000
b1101 2
1'
#428000
0'
#429000
b1110 2
1'
#430000
0'
#431000
b1111 2
1'
#432000
0'
#433000
b10000 2
1'
#434000
0'
#435000
b10001 2
1'
#436000
0'
#437000
b10010 2
1'
#438000
0'
#439000
b10011 2
1'
#440000
0'
#441000
b10100 2
1'
#442000
0'
#443000
b10101 2
1'
#444000
0'
#445000
b10110 2
1'
#446000
0'
#447000
b10111 2
1'
#448000
0'
#449000
b11000 2
1'
#450000
0'
#451000
b11001 2
1'
#452000
0'
#453000
0!
b11010 2
1'
#454000
0'
#455000
b11011 2
1'
#456000
0'
#457000
b11100 2
1'
#458000
0'
#459000
b11101 2
1'
#460000
0'
#461000
b11110 2
1'
#462000
0'
#463000
b11111 2
1'
#464000
0'
#465000
b100000 2
1'
#466000
0'
#467000
b100001 2
1'
#468000
0'
#469000
b100010 2
1'
#470000
0'
#471000
b100011 2
1'
#472000
0'
#473000
b100100 2
1'
#474000
0'
#475000
b100101 2
1'
#476000
0'
#477000
b100110 2
1'
#478000
0'
#479000
b100111 2
1'
#480000
0'
#481000
b101000 2
1'
#482000
0'
#483000
b101001 2
1'
#484000
0'
#485000
b101010 2
1'
#486000
0'
#487000
b101011 2
1'
#488000
0'
#489000
b101100 2
1'
#490000
0'
#491000
b101101 2
1'
#492000
0'
#493000
b101110 2
1'
#494000
0'
#495000
b101111 2
1'
#496000
0'
#497000
b110000 2
1'
#498000
0'
#499000
b110001 2
1'
#500000
0'
#501000
b110010 2
1'
#502000
0'
#503000
b110011 2
1'
#504000
0'
#505000
b110100 2
1'
#506000
0'
#507000
b110101 2
1'
#508000
0'
#509000
b110110 2
1'
#510000
0'
#511000
b110111 2
1'
#512000
0'
#513000
b111000 2
1'
#514000
0'
#515000
b111001 2
1'
#516000
0'
#517000
b111010 2
1'
#518000
0'
#519000
b111011 2
1'
#520000
0'
#521000
b111100 2
1'
#522000
0'
#523000
b111101 2
1'
#524000
0'
#525000
b111110 2
1'
#526000
0'
#527000
b111111 2
1'
#528000
0'
#529000
b1000000 2
1'
#530000
0'
#531000
b1000001 2
1'
#532000
0'
#533000
b1000010 2
1'
#534000
0'
#535000
b1000011 2
1'
#536000
0'
#537000
b1000100 2
1'
#538000
0'
#539000
b1000101 2
1'
#540000
0'
#541000
b1000110 2
1'
#542000
0'
#543000
b1000111 2
1'
#544000
0'
#545000
b1001000 2
1'
#546000
0'
#547000
b1001001 2
1'
#548000
0'
#549000
b1001010 2
1'
#550000
0'
#551000
b1001011 2
1'
#552000
0'
#553000
b1001100 2
1'
#554000
0'
#555000
b1001101 2
1'
#556000
0'
#557000
b1001110 2
1'
#558000
0'
#559000
b1001111 2
1'
#560000
0'
#561000
b1010000 2
1'
#562000
0'
#563000
b1010001 2
1'
#564000
0'
#565000
b1010010 2
1'
#566000
0'
#567000
b1010011 2
1'
#568000
0'
#569000
b1010100 2
1'
#570000
0'
#571000
b1010101 2
1'
#572000
0'
#573000
b1010110 2
1'
#574000
0'
#575000
b1010111 2
1'
#576000
0'
#577000
b1011000 2
1'
#578000
0'
#579000
b1011001 2
1'
#580000
0'
#581000
b1011010 2
1'
#582000
0'
#583000
b1011011 2
1'
#584000
0'
#585000
b1011100 2
1'
#586000
0'
#587000
b1011101 2
1'
#588000
0'
#589000
b1011110 2
1'
#590000
0'
#591000
b1011111 2
1'
#592000
0'
#593000
b1100000 2
1'
#594000
0'
#595000
b1100001 2
1'
#596000
0'
#597000
b1100010 2
1'
#598000
0'
#599000
b1100011 2
1'
#600000
0'
#601000
b0 2
1'
#602000
0'
#603000
1!
b1 2
b110010000 -
b0 ,
b1100100 5
b100 6
1'
#604000
0'
#605000
b10 2
b1 ,
1'
#606000
0'
#607000
b11 2
b10 ,
1'
#608000
0'
#609000
b100 2
b11 ,
1'
#610000
0'
#611000
b101 2
b100 ,
1'
#612000
0'
#613000
b110 2
b101 ,
1'
#614000
0'
#615000
b111 2
b110 ,
1'
#616000
0'
#617000
b1000 2
b111 ,
1'
#618000
0'
#619000
b1001 2
b1000 ,
1'
#620000
0'
#621000
b1010 2
b1001 ,
1'
#622000
0'
#623000
b1011 2
b1010 ,
1'
#624000
0'
#625000
b1100 2
b1011 ,
1'
#626000
0'
#627000
b1101 2
b1100 ,
1'
#628000
0'
#629000
b1110 2
b1101 ,
1'
#630000
0'
#631000
b1111 2
b1110 ,
1'
#632000
0'
#633000
b10000 2
b1111 ,
1'
#634000
0'
#635000
b10001 2
b10000 ,
1'
#636000
0'
#637000
b10010 2
b10001 ,
1'
#638000
0'
#639000
b10011 2
b10010 ,
1'
#640000
0'
#641000
b10100 2
b10011 ,
1'
#642000
0'
#643000
b10101 2
b10100 ,
1'
#644000
0'
#645000
b10110 2
b10101 ,
1'
#646000
0'
#647000
b10111 2
b10110 ,
1'
#648000
0'
#649000
b11000 2
b10111 ,
1'
#650000
0'
#651000
b11001 2
b11000 ,
1'
#652000
0'
#653000
0!
b11010 2
b11001 ,
1'
#654000
0'
#655000
b11011 2
1'
#656000
0'
#657000
b11100 2
1'
#658000
0'
#659000
b11101 2
1'
#660000
0'
#661000
b11110 2
1'
#662000
0'
#663000
b11111 2
1'
#664000
0'
#665000
b100000 2
1'
#666000
0'
#667000
b100001 2
1'
#668000
0'
#669000
b100010 2
1'
#670000
0'
#671000
b100011 2
1'
#672000
0'
#673000
b100100 2
1'
#674000
0'
#675000
b100101 2
1'
#676000
0'
#677000
b100110 2
1'
#678000
0'
#679000
b100111 2
1'
#680000
0'
#681000
b101000 2
1'
#682000
0'
#683000
b101001 2
1'
#684000
0'
#685000
b101010 2
1'
#686000
0'
#687000
b101011 2
1'
#688000
0'
#689000
b101100 2
1'
#690000
0'
#691000
b101101 2
1'
#692000
0'
#693000
b101110 2
1'
#694000
0'
#695000
b101111 2
1'
#696000
0'
#697000
b110000 2
1'
#698000
0'
#699000
b110001 2
1'
#700000
0'
#701000
b110010 2
1'
#702000
0'
#703000
b110011 2
1'
#704000
0'
#705000
b110100 2
1'
#706000
0'
#707000
b110101 2
1'
#708000
0'
#709000
b110110 2
1'
#710000
0'
#711000
b110111 2
1'
#712000
0'
#713000
b111000 2
1'
#714000
0'
#715000
b111001 2
1'
#716000
0'
#717000
b111010 2
1'
#718000
0'
#719000
b111011 2
1'
#720000
0'
#721000
b111100 2
1'
#722000
0'
#723000
b111101 2
1'
#724000
0'
#725000
b111110 2
1'
#726000
0'
#727000
b111111 2
1'
#728000
0'
#729000
b1000000 2
1'
#730000
0'
#731000
b1000001 2
1'
#732000
0'
#733000
b1000010 2
1'
#734000
0'
#735000
b1000011 2
1'
#736000
0'
#737000
b1000100 2
1'
#738000
0'
#739000
b1000101 2
1'
#740000
0'
#741000
b1000110 2
1'
#742000
0'
#743000
b1000111 2
1'
#744000
0'
#745000
b1001000 2
1'
#746000
0'
#747000
b1001001 2
1'
#748000
0'
#749000
b1001010 2
1'
#750000
0'
#751000
b1001011 2
1'
#752000
0'
#753000
b1001100 2
1'
#754000
0'
#755000
b1001101 2
1'
#756000
0'
#757000
b1001110 2
1'
#758000
0'
#759000
b1001111 2
1'
#760000
0'
#761000
b1010000 2
1'
#762000
0'
#763000
b1010001 2
1'
#764000
0'
#765000
b1010010 2
1'
#766000
0'
#767000
b1010011 2
1'
#768000
0'
#769000
b1010100 2
1'
#770000
0'
#771000
b1010101 2
1'
#772000
0'
#773000
b1010110 2
1'
#774000
0'
#775000
b1010111 2
1'
#776000
0'
#777000
b1011000 2
1'
#778000
0'
#779000
b1011001 2
1'
#780000
0'
#781000
b1011010 2
1'
#782000
0'
#783000
b1011011 2
1'
#784000
0'
#785000
b1011100 2
1'
#786000
0'
#787000
b1011101 2
1'
#788000
0'
#789000
b1011110 2
1'
#790000
0'
#791000
b1011111 2
1'
#792000
0'
#793000
b1100000 2
1'
#794000
0'
#795000
b1100001 2
1'
#796000
0'
#797000
b1100010 2
1'
#798000
0'
#799000
b1100011 2
1'
#800000
0'
#801000
b0 2
1'
#802000
0'
#803000
1!
b1 2
1'
#804000
0'
#805000
b10 2
b11010 ,
1'
#806000
0'
#807000
b11 2
b11011 ,
1'
#808000
0'
#809000
b100 2
b11100 ,
1'
#810000
0'
#811000
b101 2
b11101 ,
1'
#812000
0'
#813000
b110 2
b11110 ,
1'
#814000
0'
#815000
b111 2
b11111 ,
1'
#816000
0'
#817000
b1000 2
b100000 ,
1'
#818000
0'
#819000
b1001 2
b100001 ,
1'
#820000
0'
#821000
b1010 2
b100010 ,
1'
#822000
0'
#823000
b1011 2
b100011 ,
1'
#824000
0'
#825000
b1100 2
b100100 ,
1'
#826000
0'
#827000
b1101 2
b100101 ,
1'
#828000
0'
#829000
b1110 2
b100110 ,
1'
#830000
0'
#831000
b1111 2
b100111 ,
1'
#832000
0'
#833000
b10000 2
b101000 ,
1'
#834000
0'
#835000
b10001 2
b101001 ,
1'
#836000
0'
#837000
b10010 2
b101010 ,
1'
#838000
0'
#839000
b10011 2
b101011 ,
1'
#840000
0'
#841000
b10100 2
b101100 ,
1'
#842000
0'
#843000
b10101 2
b101101 ,
1'
#844000
0'
#845000
b10110 2
b101110 ,
1'
#846000
0'
#847000
b10111 2
b101111 ,
1'
#848000
0'
#849000
b11000 2
b110000 ,
1'
#850000
0'
#851000
b11001 2
b110001 ,
1'
#852000
0'
#853000
0!
b11010 2
b110010 ,
1'
#854000
0'
#855000
b11011 2
1'
#856000
0'
#857000
b11100 2
1'
#858000
0'
#859000
b11101 2
1'
#860000
0'
#861000
b11110 2
1'
#862000
0'
#863000
b11111 2
1'
#864000
0'
#865000
b100000 2
1'
#866000
0'
#867000
b100001 2
1'
#868000
0'
#869000
b100010 2
1'
#870000
0'
#871000
b100011 2
1'
#872000
0'
#873000
b100100 2
1'
#874000
0'
#875000
b100101 2
1'
#876000
0'
#877000
b100110 2
1'
#878000
0'
#879000
b100111 2
1'
#880000
0'
#881000
b101000 2
1'
#882000
0'
#883000
b101001 2
1'
#884000
0'
#885000
b101010 2
1'
#886000
0'
#887000
b101011 2
1'
#888000
0'
#889000
b101100 2
1'
#890000
0'
#891000
b101101 2
1'
#892000
0'
#893000
b101110 2
1'
#894000
0'
#895000
b101111 2
1'
#896000
0'
#897000
b110000 2
1'
#898000
0'
#899000
b110001 2
1'
#900000
0'
#901000
b110010 2
1'
#902000
0'
#903000
b110011 2
1'
#904000
0'
#905000
b110100 2
1'
#906000
0'
#907000
b110101 2
1'
#908000
0'
#909000
b110110 2
1'
#910000
0'
#911000
b110111 2
1'
#912000
0'
#913000
b111000 2
1'
#914000
0'
#915000
b111001 2
1'
#916000
0'
#917000
b111010 2
1'
#918000
0'
#919000
b111011 2
1'
#920000
0'
#921000
b111100 2
1'
#922000
0'
#923000
b111101 2
1'
#924000
0'
#925000
b111110 2
1'
#926000
0'
#927000
b111111 2
1'
#928000
0'
#929000
b1000000 2
1'
#930000
0'
#931000
b1000001 2
1'
#932000
0'
#933000
b1000010 2
1'
#934000
0'
#935000
b1000011 2
1'
#936000
0'
#937000
b1000100 2
1'
#938000
0'
#939000
b1000101 2
1'
#940000
0'
#941000
b1000110 2
1'
#942000
0'
#943000
b1000111 2
1'
#944000
0'
#945000
b1001000 2
1'
#946000
0'
#947000
b1001001 2
1'
#948000
0'
#949000
b1001010 2
1'
#950000
0'
#951000
b1001011 2
1'
#952000
0'
#953000
b1001100 2
1'
#954000
0'
#955000
b1001101 2
1'
#956000
0'
#957000
b1001110 2
1'
#958000
0'
#959000
b1001111 2
1'
#960000
0'
#961000
b1010000 2
1'
#962000
0'
#963000
b1010001 2
1'
#964000
0'
#965000
b1010010 2
1'
#966000
0'
#967000
b1010011 2
1'
#968000
0'
#969000
b1010100 2
1'
#970000
0'
#971000
b1010101 2
1'
#972000
0'
#973000
b1010110 2
1'
#974000
0'
#975000
b1010111 2
1'
#976000
0'
#977000
b1011000 2
1'
#978000
0'
#979000
b1011001 2
1'
#980000
0'
#981000
b1011010 2
1'
#982000
0'
#983000
b1011011 2
1'
#984000
0'
#985000
b1011100 2
1'
#986000
0'
#987000
b1011101 2
1'
#988000
0'
#989000
b1011110 2
1'
#990000
0'
#991000
b1011111 2
1'
#992000
0'
#993000
b1100000 2
1'
#994000
0'
#995000
b1100001 2
1'
#996000
0'
#997000
b1100010 2
1'
#998000
0'
#999000
b1100011 2
1'
#1000000
0'
#1001000
b0 2
1'
#1002000
0'
#1003000
1!
b1 2
1'
#1004000
0'
#1005000
b10 2
b110011 ,
1'
#1006000
0'
#1007000
b11 2
b110100 ,
1'
#1008000
0'
#1009000
b100 2
b110101 ,
1'
#1010000
0'
#1011000
b101 2
b110110 ,
1'
#1012000
0'
#1013000
b110 2
b110111 ,
1'
#1014000
0'
#1015000
b111 2
b111000 ,
1'
#1016000
0'
#1017000
b1000 2
b111001 ,
1'
#1018000
0'
#1019000
b1001 2
b111010 ,
1'
#1020000
0'
#1021000
b1010 2
b111011 ,
1'
#1022000
0'
#1023000
b1011 2
b111100 ,
1'
#1024000
0'
#1025000
b1100 2
b111101 ,
1'
#1026000
0'
#1027000
b1101 2
b111110 ,
1'
#1028000
0'
#1029000
b1110 2
b111111 ,
1'
#1030000
0'
#1031000
b1111 2
b1000000 ,
1'
#1032000
0'
#1033000
b10000 2
b1000001 ,
1'
#1034000
0'
#1035000
b10001 2
b1000010 ,
1'
#1036000
0'
#1037000
b10010 2
b1000011 ,
1'
#1038000
0'
#1039000
b10011 2
b1000100 ,
1'
#1040000
0'
#1041000
b10100 2
b1000101 ,
1'
#1042000
0'
#1043000
b10101 2
b1000110 ,
1'
#1044000
0'
#1045000
b10110 2
b1000111 ,
1'
#1046000
0'
#1047000
b10111 2
b1001000 ,
1'
#1048000
0'
#1049000
b11000 2
b1001001 ,
1'
#1050000
0'
#1051000
b11001 2
b1001010 ,
1'
#1052000
0'
#1053000
0!
b11010 2
b1001011 ,
1'
#1054000
0'
#1055000
b11011 2
1'
#1056000
0'
#1057000
b11100 2
1'
#1058000
0'
#1059000
b11101 2
1'
#1060000
0'
#1061000
b11110 2
1'
#1062000
0'
#1063000
b11111 2
1'
#1064000
0'
#1065000
b100000 2
1'
#1066000
0'
#1067000
b100001 2
1'
#1068000
0'
#1069000
b100010 2
1'
#1070000
0'
#1071000
b100011 2
1'
#1072000
0'
#1073000
b100100 2
1'
#1074000
0'
#1075000
b100101 2
1'
#1076000
0'
#1077000
b100110 2
1'
#1078000
0'
#1079000
b100111 2
1'
#1080000
0'
#1081000
b101000 2
1'
#1082000
0'
#1083000
b101001 2
1'
#1084000
0'
#1085000
b101010 2
1'
#1086000
0'
#1087000
b101011 2
1'
#1088000
0'
#1089000
b101100 2
1'
#1090000
0'
#1091000
b101101 2
1'
#1092000
0'
#1093000
b101110 2
1'
#1094000
0'
#1095000
b101111 2
1'
#1096000
0'
#1097000
b110000 2
1'
#1098000
0'
#1099000
b110001 2
1'
#1100000
0'
#1101000
b110010 2
1'
#1102000
0'
#1103000
b110011 2
1'
#1104000
0'
